{
    "nombre": "CATEGORIAS_MARCA",
    "descripcion": "Información relacionada con categorías de marca",
    "opciones": [
        {"valor": "ropa", "label": "Ropa"},
        {"valor": "calzado", "label": "Calzado"},
        {"valor": "accesorios", "label": "Accesorios"},
        {"valor": "tecnologia", "label": "Tecnología"},
        {"valor": "hogar", "label": "Hogar"},
        {"valor": "deportes", "label": "Deportes"},
        {"valor": "belleza", "label": "Belleza"},
        {"valor": "alimentacion", "label": "Alimentación"},
        {"valor": "automoviles", "label": "Automóviles"},
        {"valor": "juegos", "label": "Juegos"},
        {"valor": "libros", "label": "Libros"},
        {"valor": "musica", "label": "Música"},
        {"valor": "viajes", "label": "Viajes"},
        {"valor": "entretenimiento", "label": "Entretenimiento"},
        {"valor": "salud", "label": "Salud"},
        {"valor": "joyeria", "label": "Joyería"},
        {"valor": "muebles", "label": "Muebles"},
        {"valor": "arte", "label": "Arte"},
        {"valor": "educacion", "label": "Educación"},
        {"valor": "animales_mascotas", "label": "Animales y Mascotas"},
        {"valor": "electronica", "label": "Electrónica"},
        {"valor": "bebidas", "label": "Bebidas"},
        {"valor": "juguetes", "label": "Juguetes"},
        {"valor": "television_cine", "label": "Televisión y Cine"},
        {"valor": "software", "label": "Software"},
        {"valor": "equipamiento_deportivo", "label": "Equipamiento Deportivo"},
        {"valor": "bicicletas", "label": "Bicicletas"},
        {"valor": "telecomunicaciones", "label": "Telecomunicaciones"},
        {"valor": "cosmeticos", "label": "Cosméticos"},
        {"valor": "relojes", "label": "Relojes"},
        {"valor": "automatizacion_hogar", "label": "Automatización del Hogar"},
        {"valor": "fotografia", "label": "Fotografía"},
        {"valor": "educacion_online", "label": "Educación en línea"},
        {"valor": "hobbies", "label": "Hobbies"},
        {"valor": "agricultura", "label": "Agricultura"},
        {"valor": "vehiculos_aereos", "label": "Vehículos Aéreos"},
        {"valor": "moda_sostenible", "label": "Moda Sostenible"},
        {"valor": "diseño_interior", "label": "Diseño de Interior"},
        {"valor": "vehiculos_electricos", "label": "Vehículos Eléctricos"},
        {"valor": "alquiler_vacacional", "label": "Alquiler Vacacional"},
        {"valor": "jardineria", "label": "Jardinería"},
        {"valor": "teatro", "label": "Teatro"},
        {"valor": "biotecnologia", "label": "Biotecnología"},
        {"valor": "ciencia", "label": "Ciencia"},
        {"valor": "tecnologia_espacial", "label": "Tecnología Espacial"},
        {"valor": "mascotas_exoticas", "label": "Mascotas Exóticas"},
        {"valor": "ciencia_ficcion", "label": "Ciencia Ficción"},
        {"valor": "sostenibilidad_ambiental", "label": "Sostenibilidad Ambiental"},
        {"valor": "otras", "label": "Otras"}
    ]
}
